MANIFEST.in
README.rst
setup.py
tests/__init__.py
tests/base.py
tests/common.py
tests/libs.py
tests/zeta.py
zetalibrary/__init__.py
zetalibrary/__init__.pyc
zetalibrary/main.py
zetalibrary/packer.py
zetalibrary/packer.pyc
zetalibrary/parser.py
zetalibrary/parser.pyc
zetalibrary/settings.py
zetalibrary/settings.pyc
zetalibrary/shell.sh
zetalibrary/utils.py
zetalibrary/utils.pyc
zetalibrary.egg-info/PKG-INFO
zetalibrary.egg-info/SOURCES.txt
zetalibrary.egg-info/dependency_links.txt
zetalibrary.egg-info/entry_points.txt
zetalibrary.egg-info/requires.txt
zetalibrary.egg-info/top_level.txt
zetalibrary/libs/.gitignore
zetalibrary/libs/.tags
zetalibrary/libs/Makefile
zetalibrary/libs/README.rst
zetalibrary/libs/_compass.scss
zetalibrary/libs/blueprint.css
zetalibrary/libs/boilerplate.css
zetalibrary/libs/compass.scss
zetalibrary/libs/jquery.js
zetalibrary/libs/underscore.js
zetalibrary/libs/zeta.css
zetalibrary/libs/zeta.js
zetalibrary/libs/.git/COMMIT_EDITMSG
zetalibrary/libs/.git/HEAD
zetalibrary/libs/.git/config
zetalibrary/libs/.git/description
zetalibrary/libs/.git/index
zetalibrary/libs/.git/packed-refs
zetalibrary/libs/.git/hooks/applypatch-msg.sample
zetalibrary/libs/.git/hooks/commit-msg.sample
zetalibrary/libs/.git/hooks/post-commit.sample
zetalibrary/libs/.git/hooks/post-receive.sample
zetalibrary/libs/.git/hooks/post-update.sample
zetalibrary/libs/.git/hooks/pre-applypatch.sample
zetalibrary/libs/.git/hooks/pre-commit.sample
zetalibrary/libs/.git/hooks/pre-rebase.sample
zetalibrary/libs/.git/hooks/prepare-commit-msg.sample
zetalibrary/libs/.git/hooks/update.sample
zetalibrary/libs/.git/info/exclude
zetalibrary/libs/.git/logs/HEAD
zetalibrary/libs/.git/logs/refs/heads/master
zetalibrary/libs/.git/logs/refs/remotes/origin/master
zetalibrary/libs/.git/objects/03/ea03735e40d98398a2586b4a8da3321540c0fd
zetalibrary/libs/.git/objects/22/60e02eef244ec3bfb8fbfdcc49df38eb421cc6
zetalibrary/libs/.git/objects/2c/257d4b2627ea4d3e9ea1d14f305cb96228feb7
zetalibrary/libs/.git/objects/3a/5e68b92aa586a81794d2efd2e04a4b19aa2bc7
zetalibrary/libs/.git/objects/5e/3dc515d455b0dea7b9d88519016298c9055bb5
zetalibrary/libs/.git/objects/83/4763b7d1060af7a19d2dace2f61b8e44af3ca8
