Metadata-Version: 1.1
Name: zetalibrary
Version: 0.5.93
Summary: Zeta library is css, js framework.
